hydro_serving_grpc/.gitignore
hydro_serving_grpc/__init__.py
hydro_serving_grpc/interpretability/__init__.py
hydro_serving_grpc/interpretability/visualization/__init__.py
hydro_serving_grpc/interpretability/visualization/api_pb2.py
hydro_serving_grpc/interpretability/visualization/api_pb2_grpc.py
hydro_serving_grpc/monitoring/__init__.py
hydro_serving_grpc/monitoring/auto_od/__init__.py
hydro_serving_grpc/monitoring/auto_od/api_pb2.py
hydro_serving_grpc/monitoring/auto_od/api_pb2_grpc.py
hydro_serving_grpc/monitoring/sonar/__init__.py
hydro_serving_grpc/monitoring/sonar/api_pb2.py
hydro_serving_grpc/monitoring/sonar/api_pb2_grpc.py
hydro_serving_grpc/monitoring/sonar/entities_pb2.py
hydro_serving_grpc/monitoring/sonar/entities_pb2_grpc.py
hydro_serving_grpc/serving/__init__.py
hydro_serving_grpc/serving/contract/__init__.py
hydro_serving_grpc/serving/contract/field_pb2.py
hydro_serving_grpc/serving/contract/field_pb2_grpc.py
hydro_serving_grpc/serving/contract/signature_pb2.py
hydro_serving_grpc/serving/contract/signature_pb2_grpc.py
hydro_serving_grpc/serving/contract/tensor_pb2.py
hydro_serving_grpc/serving/contract/tensor_pb2_grpc.py
hydro_serving_grpc/serving/contract/types_pb2.py
hydro_serving_grpc/serving/contract/types_pb2_grpc.py
hydro_serving_grpc/serving/discovery/__init__.py
hydro_serving_grpc/serving/discovery/api_pb2.py
hydro_serving_grpc/serving/discovery/api_pb2_grpc.py
hydro_serving_grpc/serving/gateway/__init__.py
hydro_serving_grpc/serving/gateway/api_pb2.py
hydro_serving_grpc/serving/gateway/api_pb2_grpc.py
hydro_serving_grpc/serving/manager/__init__.py
hydro_serving_grpc/serving/manager/api_pb2.py
hydro_serving_grpc/serving/manager/api_pb2_grpc.py
hydro_serving_grpc/serving/manager/entities_pb2.py
hydro_serving_grpc/serving/manager/entities_pb2_grpc.py
hydro_serving_grpc/serving/runtime/__init__.py
hydro_serving_grpc/serving/runtime/api_pb2.py
hydro_serving_grpc/serving/runtime/api_pb2_grpc.py
hydro_serving_grpc-3.0.3.dist-info/WHEEL
hydro_serving_grpc-3.0.3.dist-info/METADATA
hydro_serving_grpc-3.0.3.dist-info/RECORD
