Metadata-Version: 2.1
Name: hydro-serving-grpc
Version: 3.0.3
Summary: Protobuf messages and GRPC API for Hydrosphere Serving platform
Home-page: https://github.com/Hydrospheredata/hydro-serving-protos
License: Apache 2.0
Author: Hydrospheredata
Author-email: info@hydrosphere.io
Requires-Python: >=3.6,<4.0
Classifier: License :: OSI Approved :: Apache Software License
Classifier: License :: Other/Proprietary License
Classifier: Natural Language :: English
Classifier: Programming Language :: Python
Classifier: Programming Language :: Python :: 3
Classifier: Programming Language :: Python :: 3.10
Classifier: Programming Language :: Python :: 3.6
Classifier: Programming Language :: Python :: 3.7
Classifier: Programming Language :: Python :: 3.8
Classifier: Programming Language :: Python :: 3.9
Requires-Dist: grpcio (>=1.41.0,<2.0.0)
Requires-Dist: protobuf (>=3.17.2,<4.0.0)
Project-URL: Repository, https://github.com/Hydrospheredata/hydro-serving-protos
